{
  "attributes": [
    {
      "default": "fragment(\"gen_random_uuid()\")",
      "size": null,
      "type": "uuid",
      "source": "id",
      "references": null,
      "allow_nil?": false,
      "primary_key?": true,
      "generated?": false
    },
    {
      "default": "fragment(\"(now() AT TIME ZONE 'utc')\")",
      "size": null,
      "type": "utc_datetime_usec",
      "source": "created_at",
      "references": null,
      "allow_nil?": false,
      "primary_key?": false,
      "generated?": false
    },
    {
      "default": "nil",
      "size": null,
      "type": "text",
      "source": "absolute_path",
      "references": null,
      "allow_nil?": true,
      "primary_key?": false,
      "generated?": false
    },
    {
      "default": "nil",
      "size": null,
      "type": "binary",
      "source": "content_hash",
      "references": null,
      "allow_nil?": false,
      "primary_key?": false,
      "generated?": false
    },
    {
      "default": "nil",
      "size": null,
      "type": "uuid",
      "source": "source_id",
      "references": {
        "name": "documents_source_id_fkey",
        "table": "sources",
        "primary_key?": true,
        "on_delete": "delete",
        "schema": "public",
        "multitenancy": {
          "global": null,
          "attribute": null,
          "strategy": null
        },
        "destination_attribute": "id",
        "on_update": null,
        "deferrable": false,
        "match_with": null,
        "match_type": null,
        "index?": false,
        "destination_attribute_default": null,
        "destination_attribute_generated": null
      },
      "allow_nil?": true,
      "primary_key?": false,
      "generated?": false
    }
  ],
  "table": "documents",
  "hash": "EED9926911A080ABA1D87DAF1B24EC0B53FADFCF36B6D533ABF4AA93C93CA80A",
  "repo": "Elixir.Canary.Repo",
  "schema": null,
  "base_filter": null,
  "check_constraints": [],
  "identities": [
    {
      "name": "unique_content",
      "keys": [
        {
          "type": "atom",
          "value": "content_hash"
        }
      ],
      "where": null,
      "base_filter": null,
      "all_tenants?": false,
      "nils_distinct?": true,
      "index_name": "documents_unique_content_index"
    }
  ],
  "custom_indexes": [],
  "multitenancy": {
    "global": null,
    "attribute": null,
    "strategy": null
  },
  "custom_statements": [],
  "has_create_action": true
}
