{
  "attributes": [
    {
      "default": "fragment(\"gen_random_uuid()\")",
      "size": null,
      "type": "uuid",
      "source": "id",
      "references": null,
      "allow_nil?": false,
      "primary_key?": true,
      "generated?": false
    },
    {
      "default": "nil",
      "size": null,
      "type": "uuid",
      "source": "user_id",
      "references": null,
      "allow_nil?": false,
      "primary_key?": false,
      "generated?": false
    },
    {
      "default": "nil",
      "size": null,
      "type": "text",
      "source": "name",
      "references": null,
      "allow_nil?": false,
      "primary_key?": false,
      "generated?": false
    }
  ],
  "table": "accounts",
  "hash": "D33A99515799BA11B3F968608A7D5410DD8BD774728DFDB18743EEE4323C6A01",
  "repo": "Elixir.Canary.Repo",
  "identities": [],
  "schema": null,
  "base_filter": null,
  "check_constraints": [],
  "custom_indexes": [],
  "multitenancy": {
    "global": null,
    "strategy": null,
    "attribute": null
  },
  "custom_statements": [],
  "has_create_action": true
}